ClipMaster/ClipMaster.py
ClipMaster/__init__.py
ClipMaster-0.0.0.0.3.dist-info/LICENSE
ClipMaster-0.0.0.0.3.dist-info/METADATA
ClipMaster-0.0.0.0.3.dist-info/WHEEL
ClipMaster-0.0.0.0.3.dist-info/top_level.txt
ClipMaster-0.0.0.0.3.dist-info/RECORD
