Metadata-Version: 2.1
Name: ClipMaster
Version: 0.0.0.0.3
Summary: UNKNOWN
Home-page: https://github.com/ShaonMajumder/ClipMaster
Author: Shaon Majumder
Author-email: smazoomder@gmail.com
License: UNKNOWN
Download-URL: https://github.com/ShaonMajumder/ClipMaster/archive/0.0.0.0.3.tar.gz
Keywords: shaon,video editing
Platform: UNKNOWN
